alfen_eve_modbus_tcp/__init__.py
alfen_eve_modbus_tcp-0.0.15.dist-info/LICENSE
alfen_eve_modbus_tcp-0.0.15.dist-info/METADATA
alfen_eve_modbus_tcp-0.0.15.dist-info/WHEEL
alfen_eve_modbus_tcp-0.0.15.dist-info/top_level.txt
alfen_eve_modbus_tcp-0.0.15.dist-info/RECORD
