Metadata-Version: 2.1
Name: alfen-eve-modbus-tcp
Version: 0.0.15
Summary: Alfen Eve Car Charger parser library
Home-page: https://github.com/nessnaj/alfen_eve_modbus_tcp
Author: nessnaj
License: MIT License
Project-URL: Issue Tracker, https://github.com/nessnaj/alfen_eve_modbus_tcp/issues
Classifier: Development Status :: 4 - Beta
Classifier: Programming Language :: Python :: 3.11
Classifier: Operating System :: OS Independent
Classifier: Environment :: Console
Classifier: Natural Language :: English
Classifier: Intended Audience :: Developers
Classifier: License :: OSI Approved :: MIT License
Requires-Python: >=3.9
License-File: LICENSE
Requires-Dist: pymodbus <3.7.0,>=3.5.0
Requires-Dist: pyserial-asyncio >=0.6.0
